suricata_language_server-1.3.1.dist-info/licenses/LICENSE
suricatals/__init__.py
suricatals/jsonrpc.py
suricatals/langserver.py
suricatals/lsp_helpers.py
suricatals/parse_signatures.py
suricatals/suri_cmd.py
suricatals/tests_rules.py
suricatals/tokenize_sig.py
suricatals/unit_tests.py
suricatals/data/suricata-keywords.json
suricata_language_server-1.3.1.dist-info/METADATA
suricata_language_server-1.3.1.dist-info/WHEEL
suricata_language_server-1.3.1.dist-info/entry_points.txt
suricata_language_server-1.3.1.dist-info/top_level.txt
suricata_language_server-1.3.1.dist-info/RECORD
