Metadata-Version: 2.4
Name: suricata-language-server
Version: 1.3.1
Summary: Language Server Protocol for Suricata signatures
Author-email: Eric Leblond <el@stamus-networks.com>, Nicolas Frisoni <nfrisoni@stamus-networks.com>
Maintainer-email: Eric Leblond <el@stamus-networks.com>
Project-URL: Homepage, https://www.stamus-networks.com/suricata-language-server
Project-URL: Issues, https://github.com/StamusNetworks/suricata-language-server/issues
Project-URL: Repository, https://github.com/StamusNetworks/suricata-language-server.git
Keywords: suricata,language-server-protocol,lsp,signature,ids,ips
Classifier: Programming Language :: Python :: 3
Classifier: Development Status :: 5 - Production/Stable
Classifier: Environment :: No Input/Output (Daemon)
Classifier: Intended Audience :: Information Technology
Classifier: Operating System :: OS Independent
Classifier: Topic :: Security
Requires-Python: >=3.7
License-File: LICENSE
Requires-Dist: docker>=7.1.0
Dynamic: license-file
